vade_api-0.9.3.data/scripts/vade_api
vade_api_src/__init__.py
vade_api_src/realtime.py
vade_api_src/spot_structs.py
vade_api_src/vade_enums.py
vade_api_src/resources/__init__.py
vade_api_src/resources/default_vade_image.jpg
vade_api-0.9.3.dist-info/LICENSE
vade_api-0.9.3.dist-info/METADATA
vade_api-0.9.3.dist-info/WHEEL
vade_api-0.9.3.dist-info/top_level.txt
vade_api-0.9.3.dist-info/RECORD
