Metadata-Version: 2.1
Name: vade-api
Version: 0.9.3
Summary: An easy to use wrapper for vade realtime api
Home-page: UNKNOWN
Author: Christain Burke
Author-email: christian@vadepark.com
License: UNKNOWN
Platform: UNKNOWN
Classifier: Programming Language :: Python :: 3
Classifier: License :: OSI Approved :: MIT License
Classifier: Operating System :: OS Independent
Requires-Dist: pytz
Requires-Dist: tzwhere
Requires-Dist: requests
Requires-Dist: python-dateutil
Requires-Dist: webcolors
